gs1/__init__.py
gs1/utils.py
gs1/compress/__init__.py
gs1/compress/build_compressed_gs1_digital_link.py
gs1/compress/core_functions.py
gs1/compress/encode_binary_value.py
gs1/compress/extract_from_element_strings.py
gs1/compress/utils.py
gs1/constants/__init__.py
gs1/constants/ai_table.py
gs1/constants/alphabet.py
gs1/constants/fixed_length_table.py
gs1/constants/path_sequence_constraints.py
gs1/constants/regular_expressions.py
gs1/constants/semantics.py
gs1/constants/table_f.py
gs1/constants/table_opt.py
gs1/constants/table_p.py
gs1/constants/table_s1.py
gs1/decompress/__init__.py
gs1/decompress/analyse_uri.py
gs1/decompress/binary_to_gs1_ai_array.py
gs1/decompress/build_gs1_digital_link.py
gs1/decompress/build_gs1_element_strings.py
gs1/decompress/build_structured_array.py
gs1/decompress/core_functions.py
gs1/decompress/deal_with_duplicates.py
gs1/decompress/decode_binary_value.py
gs1/decompress/extract.py
tests/__init__.py
tests/compress/__init__.py
tests/compress/test_core_functions.py
tests/compress/test_utils.py
tests/decompress/__init__.py
tests/decompress/test_analyse.py
tests/decompress/test_build_digital_links.py
tests/decompress/test_core_functions.py
tests/decompress/test_utils.py
gs1_compression-0.1.3.dist-info/LICENSE
gs1_compression-0.1.3.dist-info/METADATA
gs1_compression-0.1.3.dist-info/WHEEL
gs1_compression-0.1.3.dist-info/top_level.txt
gs1_compression-0.1.3.dist-info/RECORD
