Metadata-Version: 2.1
Name: gs1-compression
Version: 0.1.3
Summary: A Python package to handle compression and decompression of GS1 digital links
Home-page: https://github.com/Trust-Codes-Ltd/gs1-compression
Author: Di Zhu
Author-email: di.zhu@trust.codes
License: UNKNOWN
Platform: UNKNOWN
Classifier: Programming Language :: Python :: 3
Classifier: License :: OSI Approved :: Apache Software License
Classifier: Operating System :: OS Independent
Requires-Python: >=3.6
